cryptohelp/__init__.py
cryptohelp/EllipticCurves/__init__.py
cryptohelp/EllipticCurves/ecdlp.py
cryptohelp/RSA/__init__.py
cryptohelp/RSA/factorDBFunctions.py
cryptohelp-0.0.16.dist-info/LICENSE
cryptohelp-0.0.16.dist-info/METADATA
cryptohelp-0.0.16.dist-info/WHEEL
cryptohelp-0.0.16.dist-info/top_level.txt
cryptohelp-0.0.16.dist-info/RECORD
